<Properties StartupConfiguration="{BC9B0439-7075-4806-8492-021AEEA919CB}|https">
  <MonoDevelop.Ide.Workbench ActiveDocument="WebApp/Pages/Index.cshtml">
    <Files>
      <File FileName="WebApp/Pages/Index.cshtml" Line="12" Column="1" />
    </Files>
    <Pads>
      <Pad Id="ProjectPad">
        <State name="__root__">
          <Node name="WebApp" expanded="True">
            <Node name="WebApp" expanded="True">
              <Node name="Pages" expanded="True">
                <Node name="Index.cshtml" selected="True" />
              </Node>
            </Node>
          </Node>
        </State>
      </Pad>
    </Pads>
  </MonoDevelop.Ide.Workbench>
  <MonoDevelop.Ide.DebuggingService.PinnedWatches />
  <MonoDevelop.Ide.Workspace ActiveConfiguration="Debug" />
  <MultiItemStartupConfigurations />
  <MonoDevelop.Ide.DebuggingService.Breakpoints>
    <BreakpointStore />
  </MonoDevelop.Ide.DebuggingService.Breakpoints>
  <MonoDevelop.Ide.ItemProperties.WebApp PreferredExecutionTarget="/System/Volumes/Preboot/Cryptexes/App/System/Applications/Safari.app" />
</Properties>